stubsplit/__init__.py
stubsplit/__main__.py
stubsplit/stubsplit.py
stubsplit-0.1.dist-info/entry_points.txt
stubsplit-0.1.dist-info/LICENSE
stubsplit-0.1.dist-info/WHEEL
stubsplit-0.1.dist-info/METADATA
stubsplit-0.1.dist-info/RECORD
